BRACoD/BRACoD.py
BRACoD/__init__.py
BRACoD/simulations.py
BRACoD/data/OTUCounts_obesitystudy.csv
BRACoD/data/SCFA_obesitystudy.csv
BRACoD/data/Taxonomy.csv
BRACoD/data/__init__.py
data/OTUCounts_obesitystudy.csv
data/__init__.py
BRACoD-0.3.6.dist-info/METADATA
BRACoD-0.3.6.dist-info/WHEEL
BRACoD-0.3.6.dist-info/top_level.txt
BRACoD-0.3.6.dist-info/RECORD
