Metadata-Version: 2.1
Name: BRACoD
Version: 0.3.6
Summary: BRACoD is a method to identify associations between bacteria and physiological variables in Microbiome data
Home-page: https://github.com/ajverster/BRACoD/tree/main
Author: ['Adrian Verster']
Author-email: adrian.verster@hc-sc.gc.ca
License: UNKNOWN
Platform: UNKNOWN
Requires-Python: >3.6
Requires-Dist: pymc3 (==3.9.0)
Requires-Dist: pandas (>=0.24.0)
Requires-Dist: numpy (<=1.20,>=1.15)
Requires-Dist: scikit-learn (>=0.20)
Requires-Dist: arviz (<=0.10)
Requires-Dist: Theano (>=1.0.5)
